{
  "triggers": [
    {
      "id": "flow_updated",
      "title": {
        "en": "Flow status changed"
      },
      "args": [],
      "tokens": [
        {
          "name": "flow",
          "type": "number",
          "title": {
            "en": "Flow (L/min)"
          }
        }
      ]
    },
    {
      "id": "health_changed",
      "title": {
        "en": "Connection Health status changed"
      },
      "args": [],
      "tokens": [
        {
          "name": "alarm",
          "type": "boolean",
          "title": {
            "en": "Connection Health alarm"
          }
        }
      ]
    },
    {
      "id": "The ph_updated",
      "title": {
        "en": "pH changed"
      },
      "args": [],
      "tokens": [
        {
          "name": "ph",
          "type": "number",
          "title": {
            "en": "pH",
            "nl": "pH",
            "da": "pH",
            "de": "pH",
            "es": "pH",
            "fr": "pH",
            "it": "pH",
            "no": "pH",
            "sv": "pH",
            "pl": "pH",
            "ru": "pH",
            "ko": "pH"
          }
        }
      ]
    },
    {
      "id": "redox_updated",
      "title": {
        "en": "The Redox changed"
      },
      "args": [],
      "tokens": [
        {
          "name": "redox",
          "type": "number",
          "title": {
            "en": "Redox (mV)",
            "nl": "Redox (mV)",
            "da": "Redox (mV)",
            "de": "Redox (mV)",
            "es": "Redox (mV)",
            "fr": "Redox (mV)",
            "it": "Redox (mV)",
            "no": "Redoks (mV)",
            "sv": "Redox (mV)",
            "pl": "Redoks (mV)",
            "ru": "Редокс (мВ)",
            "ko": "산화 환원 전위 (mV)"
          }
        }
      ]
    }
  ],
  "conditions": [
    {
      "id": "flow_above",
      "title": {
        "en": "The Flow is above"
      },
      "args": [
        {
          "name": "threshold",
          "type": "number"
        }
      ]
    },
    {
      "id": "flow_below",
      "title": {
        "en": "The Flow is below ..."
      },
      "args": [
        {
          "name": "threshold",
          "type": "number"
        }
      ]
    },
    {
      "id": "health_ok",
      "title": {
        "en": "Connection Health"
      },
      "args": []
    },
    {
      "id": "ph_above",
      "title": {
        "en": "The pH is above ..."
      },
      "args": [
        {
          "name": "threshold",
          "type": "number"
        }
      ]
    },
    {
      "id": "ph_below",
      "title": {
        "en": "The pH is below ..."
      },
      "args": [
        {
          "name": "threshold",
          "type": "number"
        }
      ]
    },
    {
      "id": "redox_above",
      "title": {
        "en": "The Redox is above ..."
      },
      "args": [
        {
          "name": "threshold",
          "type": "number"
        }
      ]
    },
    {
      "id": "redox_below",
      "title": {
        "en": "The Redox is below ..."
      },
      "args": [
        {
          "name": "threshold",
          "type": "number"
        }
      ]
    }
  ],
  "actions": [
    {
      "id": "refresh_now",
      "title": {
        "en": "Refresh WiFi Pool now"
      },
      "args": []
    }
  ]
}